cxsystem2/__init__.py
cxsystem2/csc_puhti.job
cxsystem2/csc_puhti_sv.job
cxsystem2/cscs_daint.job
cxsystem2/bui/__init__.py
cxsystem2/bui/bui.py
cxsystem2/bui/cx_bui/__init__.py
cxsystem2/bui/cx_bui/db.sqlite3
cxsystem2/bui/cx_bui/manage.py
cxsystem2/bui/cx_bui/cx_bui/__init__.py
cxsystem2/bui/cx_bui/cx_bui/settings.py
cxsystem2/bui/cx_bui/cx_bui/urls.py
cxsystem2/bui/cx_bui/cx_bui/wsgi.py
cxsystem2/bui/cx_bui/editor/__init__.py
cxsystem2/bui/cx_bui/editor/admin.py
cxsystem2/bui/cx_bui/editor/apps.py
cxsystem2/bui/cx_bui/editor/models.py
cxsystem2/bui/cx_bui/editor/tests.py
cxsystem2/bui/cx_bui/editor/urls.py
cxsystem2/bui/cx_bui/editor/views.py
cxsystem2/bui/cx_bui/editor/migrations/__init__.py
cxsystem2/bui/cx_bui/editor/templates/editor/index.html
cxsystem2/bui/cx_bui/examples/cobaeif_anatomy_config.json
cxsystem2/bui/cx_bui/examples/cobaeif_physiology_config.json
cxsystem2/bui/cx_bui/examples/markram_step1_anatomy_config.json
cxsystem2/bui/cx_bui/examples/markram_step1_physiology_config.json
cxsystem2/bui/cx_bui/examples/markram_step2_anatomy_config.json
cxsystem2/bui/cx_bui/examples/markram_step2_physiology_config.json
cxsystem2/bui/cx_bui/examples/pytest_anatomy_config.json
cxsystem2/bui/cx_bui/examples/pytest_physiology_config.json
cxsystem2/bui/cx_bui/examples/template_anatomy_config.json
cxsystem2/bui/cx_bui/examples/template_physiology_config.json
cxsystem2/bui/cx_bui/examples/csv_configs/cobaeif_anatomy_config.csv
cxsystem2/bui/cx_bui/examples/csv_configs/cobaeif_physiology_config.csv
cxsystem2/bui/cx_bui/examples/csv_configs/markram_step1_anatomy_config.csv
cxsystem2/bui/cx_bui/examples/csv_configs/markram_step1_physiology_config.csv
cxsystem2/bui/cx_bui/examples/csv_configs/markram_step2_anatomy_config.csv
cxsystem2/bui/cx_bui/examples/csv_configs/markram_step2_physiology_config.csv
cxsystem2/bui/cx_bui/examples/csv_configs/pytest_anatomy_config.csv
cxsystem2/bui/cx_bui/examples/csv_configs/pytest_physiology_config.csv
cxsystem2-2.1.2.0.dist-info/LICENSE
cxsystem2-2.1.2.0.dist-info/METADATA
cxsystem2-2.1.2.0.dist-info/WHEEL
cxsystem2-2.1.2.0.dist-info/entry_points.txt
cxsystem2-2.1.2.0.dist-info/top_level.txt
cxsystem2-2.1.2.0.dist-info/RECORD
