Metadata-Version: 2.1
Name: cxsystem2
Version: 2.1.2.0
Summary: A cerebral cortex simulation framework
Home-page: https://github.com/VisualNeuroscience-UH/CxSystem2
Author: Vafa Andalibi, Henri Hokkanen, Simo Vanni
Author-email: vafa.andalibi@gmail.com
License: GPL v3.0
Classifier: Development Status :: 3 - Alpha
Classifier: Environment :: Win32 (MS Windows)
Classifier: Environment :: MacOS X
Classifier: Environment :: X11 Applications
Classifier: Environment :: Console
Classifier: Intended Audience :: Information Technology
Classifier: Intended Audience :: Developers
Classifier: Intended Audience :: Education
Classifier: Intended Audience :: Science/Research
Classifier: License :: OSI Approved :: GNU General Public License v3 (GPLv3)
Classifier: Natural Language :: English
Classifier: Operating System :: OS Independent
Classifier: Operating System :: MacOS
Classifier: Operating System :: Microsoft :: Windows :: Windows 10
Classifier: Operating System :: Unix
Classifier: Programming Language :: Python
Classifier: Programming Language :: Python :: 3.7
Classifier: Topic :: Scientific/Engineering
Classifier: Topic :: Scientific/Engineering :: Medical Science Apps.
Classifier: Topic :: Software Development :: Libraries
Classifier: Topic :: Utilities
Requires-Python: >=3.5
License-File: LICENSE
Requires-Dist: wheel
Requires-Dist: requests
Requires-Dist: asn1crypto
Requires-Dist: bcrypt
Requires-Dist: brian2
Requires-Dist: brian2genn
Requires-Dist: cffi
Requires-Dist: cryptography
Requires-Dist: cycler
Requires-Dist: cython
Requires-Dist: django
Requires-Dist: django-extensions
Requires-Dist: django-sslserver
Requires-Dist: docopt
Requires-Dist: ipython
Requires-Dist: jinja2
Requires-Dist: kiwisolver
Requires-Dist: markupsafe
Requires-Dist: matplotlib
Requires-Dist: mpmath
Requires-Dist: numpy
Requires-Dist: pandas
Requires-Dist: ping3
Requires-Dist: paramiko
Requires-Dist: pycparser
Requires-Dist: pynacl
Requires-Dist: pyopenssl
Requires-Dist: pyparsing
Requires-Dist: python-dateutil
Requires-Dist: pytz
Requires-Dist: scipy
Requires-Dist: scp
Requires-Dist: six
Requires-Dist: sqlparse
Requires-Dist: sympy
Requires-Dist: werkzeug
Requires-Dist: sphinx
Requires-Dist: sphinx-rtd-theme
Requires-Dist: pyyaml
